abov3/__init__.py
abov3/client.py
abov3/exceptions.py
abov3/py.typed
abov3/resources.py
abov3/types.py
abov3_ai-0.1.12.dist-info/METADATA
abov3_ai-0.1.12.dist-info/WHEEL
abov3_ai-0.1.12.dist-info/licenses/LICENSE
abov3_ai-0.1.12.dist-info/RECORD
