Metadata-Version: 2.4
Name: abov3-ai
Version: 0.1.12
Summary: Official Python SDK for ABOV3 AI - Genesis CodeForger Edition
Project-URL: Homepage, https://www.abov3.ai
Project-URL: Documentation, https://www.abov3.ai/docs
Project-URL: Repository, https://github.com/ABOV3AI/abov3-sdk-python
Project-URL: Issues, https://github.com/ABOV3AI/abov3-sdk-python/issues
Author-email: ABOV3 Team <support@abov3.ai>
License: MIT
License-File: LICENSE
Keywords: abov3,ai,api,artificial-intelligence,code-generation,developer-tools,machine-learning,sdk
Classifier: Development Status :: 4 - Beta
Classifier: Intended Audience :: Developers
Classifier: License :: OSI Approved :: MIT License
Classifier: Programming Language :: Python :: 3
Classifier: Programming Language :: Python :: 3.8
Classifier: Programming Language :: Python :: 3.9
Classifier: Programming Language :: Python :: 3.10
Classifier: Programming Language :: Python :: 3.11
Classifier: Programming Language :: Python :: 3.12
Classifier: Topic :: Scientific/Engineering :: Artificial Intelligence
Classifier: Topic :: Software Development :: Libraries :: Python Modules
Requires-Python: >=3.8
Requires-Dist: httpx>=0.24.0
Requires-Dist: pydantic>=2.0.0
Requires-Dist: typing-extensions>=4.5.0
Provides-Extra: dev
Requires-Dist: black>=23.0.0; extra == 'dev'
Requires-Dist: mypy>=1.0.0; extra == 'dev'
Requires-Dist: pytest-asyncio>=0.21.0; extra == 'dev'
Requires-Dist: pytest>=7.0.0; extra == 'dev'
Requires-Dist: ruff>=0.1.0; extra == 'dev'
